<convoy>
	<vehicle>
		<vehicle_id>10</vehicle_id>
		<engine_capacity>200</engine_capacity>
		<fuel_consumption>50</fuel_consumption>
		<maximum_load>12</maximum_load>
	</vehicle>
	<vehicle>
		<vehicle_id>11</vehicle_id>
		<engine_capacity>210</engine_capacity>
		<fuel_consumption>60</fuel_consumption>
		<maximum_load>14</maximum_load>
	</vehicle>
	<vehicle>
		<vehicle_id>12</vehicle_id>
		<engine_capacity>220</engine_capacity>
		<fuel_consumption>70</fuel_consumption>
		<maximum_load>16</maximum_load>
	</vehicle>
	<vehicle>
		<vehicle_id>13</vehicle_id>
		<engine_capacity>230</engine_capacity>
		<fuel_consumption>80</fuel_consumption>
		<maximum_load>18</maximum_load>
	</vehicle>
	<vehicle>
		<vehicle_id>14</vehicle_id>
		<engine_capacity>240</engine_capacity>
		<fuel_consumption>90</fuel_consumption>
		<maximum_load>20</maximum_load>
	</vehicle>
	<vehicle>
		<vehicle_id>24</vehicle_id>
		<engine_capacity>400</engine_capacity>
		<fuel_consumption>90</fuel_consumption>
		<maximum_load>20</maximum_load>
	</vehicle>
	<vehicle>
		<vehicle_id>26</vehicle_id>
		<engine_capacity>440</engine_capacity>
		<fuel_consumption>60</fuel_consumption>
		<maximum_load>16</maximum_load>
	</vehicle>
	<vehicle>
		<vehicle_id>27</vehicle_id>
		<engine_capacity>460</engine_capacity>
		<fuel_consumption>70</fuel_consumption>
		<maximum_load>14</maximum_load>
	</vehicle>
	<vehicle>
		<vehicle_id>28</vehicle_id>
		<engine_capacity>480</engine_capacity>
		<fuel_consumption>80</fuel_consumption>
		<maximum_load>12</maximum_load>
	</vehicle>
</convoy>